MANIFEST.in
README.md
setup.cfg
setup.py
cold_start_recommender.egg-info/PKG-INFO
cold_start_recommender.egg-info/SOURCES.txt
cold_start_recommender.egg-info/dependency_links.txt
cold_start_recommender.egg-info/requires.txt
cold_start_recommender.egg-info/top_level.txt
csrec/DALFactory.pyc
csrec/MemDAL.pyc
csrec/Observable.pyc
csrec/__init__.py
csrec/__init__.pyc
csrec/dal.py
csrec/dal.pyc
csrec/exceptions.py
csrec/exceptions.pyc
csrec/factory_dal.py
csrec/factory_dal.pyc
csrec/mem_dal.py
csrec/mem_dal.pyc
csrec/pkg_info.json~
csrec/recommender.py
csrec/recommender.pyc
csrec/tools/__init__.py
csrec/tools/__init__.pyc
csrec/tools/functions.py
csrec/tools/observable.py
csrec/tools/observable.pyc
csrec/tools/singleton.py
csrec/tools/singleton.pyc