Metadata-Version: 1.1
Name: cold-start-recommender
Version: 0.4.1
Summary: In-memory recommender for recommendations produced on-the-fly
Home-page: https://github.com/elegans-io/cold-start-recommender
Author: elegans.io Ltd
Author-email: info@elegans.io
License: GPL v2
Keywords: recommendations,recommender,recommendation engine
Platform: UNKNOWN
Classifier: Development Status :: 4 - Beta
Classifier: Intended Audience :: Information Technology
Classifier: Topic :: Scientific/Engineering :: Artificial Intelligence
Classifier: License :: OSI Approved :: GNU General Public License v2 (GPLv2)
Classifier: Programming Language :: Python :: 2.7
